copula_package/__init__.py
copula_package/copula_density.py
copuladensity_pkg-0.0.3.dist-info/LICENSE
copuladensity_pkg-0.0.3.dist-info/METADATA
copuladensity_pkg-0.0.3.dist-info/WHEEL
copuladensity_pkg-0.0.3.dist-info/top_level.txt
copuladensity_pkg-0.0.3.dist-info/RECORD
