Metadata-Version: 2.1
Name: copuladensity-pkg
Version: 0.0.3
Summary: A package for calculate and draw copula density
Home-page: https://github.com/shannwang/Copula_package
Author: Shanshan Wang
Author-email: shanshan.wang@uni-due.de
License: UNKNOWN
Project-URL: Bug Tracker, https://github.com/shannwang/Copula_package/issues
Platform: UNKNOWN
Classifier: Programming Language :: Python :: 3
Classifier: License :: OSI Approved :: MIT License
Classifier: Operating System :: OS Independent
Requires-Python: >=3.6
License-File: LICENSE
